galassify/__init__.py
galassify/config
galassify/galassify.py
galassify/gui.py
galassify/gui.ui
galassify/initgui.py
galassify/utils.py
galassify/version.py
galassify/widgets.py
galassify/files/galaxies.csv
galassify/files/galaxies_fits.csv
galassify/files/galaxies_fitsonly.csv
galassify/files/galaxies_nog.csv
galassify/files/galaxies_nog_nof.csv
galassify/files/output.csv
galassify/files/output_fits.csv
galassify/files/output_nog.csv
galassify/img/img_1_11563.jpeg
galassify/img/img_1_1432.jpeg
galassify/img/img_1_15.jpeg
galassify/img/img_1_23654.jpeg
galassify/img/img_1_254.jpeg
galassify/img/img_1_32874.jpeg
galassify/img/img_1_368.jpeg
galassify/img/img_1_45125.jpeg
galassify/img/img_1_6809.jpeg
galassify/img/img_1_87502.jpeg
galassify/img/img_1_98652.jpeg
galassify/img/img_2_12345.jpeg
galassify/img/img_2_15420.jpeg
galassify/img/img_2_18520.jpeg
galassify/img/img_2_2053.jpeg
galassify/img/img_2_23658.jpeg
galassify/img/img_2_4578.jpeg
galassify/img/img_2_54852.jpeg
galassify/img/img_2_65321.jpeg
galassify/img/img_2_76469.jpeg
galassify/img/img_2_79852.jpeg
galassify/img/img_2_91645.jpeg
galassify/img/img_4_100000.jpeg
galassify/img/img_4_15248.jpeg
galassify/img/img_4_20763.jpeg
galassify/img/img_4_28650.jpeg
galassify/img/img_4_42136.jpeg
galassify/img/img_4_46302.jpeg
galassify/img/img_4_52413.jpeg
galassify/img/img_4_63246.jpeg
galassify/img/fits/1_15_SDSS_gband.fits
galassify/img/fits/1_87502_SDSS_gband.fits
galassify/img/fits/2_18520_SDSS_gband.fits
galassify/img/fits/4_100000_SDSS_gband.fits
galassify/img/fits/4_42136_SDSS_gband.fits
galassify/img/nog/img_-_100000.jpeg
galassify/img/nog/img_-_11563.jpeg
galassify/img/nog/img_-_12345.jpeg
galassify/img/nog/img_-_1432.jpeg
galassify/img/nog/img_-_15.jpeg
galassify/img/nog/img_-_15248.jpeg
galassify/img/nog/img_-_15420.jpeg
galassify/img/nog/img_-_18520.jpeg
galassify/img/nog/img_-_2053.jpeg
galassify/img/nog/img_-_20763.jpeg
galassify/img/nog/img_-_23654.jpeg
galassify/img/nog/img_-_23658.jpeg
galassify-2.0.0.dist-info/licenses/LICENSE
galassify-2.0.0.dist-info/METADATA
galassify-2.0.0.dist-info/WHEEL
galassify-2.0.0.dist-info/entry_points.txt
galassify-2.0.0.dist-info/top_level.txt
galassify-2.0.0.dist-info/RECORD
