Metadata-Version: 2.4
Name: galassify
Version: 2.0.0
Summary: A tool to manually classify galaxies
Author-email: Manuel Alcázar-Laynez <manalclay@ugr.es>, Andoni Jimenez <andonijimenez@ugr.es>, Salvador Duarte Puertas <sduarte@ugr.es>, Cristian Pozo González <cpozo@ugr.es>, Jesús Domínguez-Gómez <jesusdg@ugr.es>, Guillermo Blázquez <gblazquez@iaa.es>, Maria del Carmen Argudo-Fernández <margudo@ugr.es>, Simon Verley <simon@ugr.es>, Daniel Espada <despada@ugr.es>, Estrella Florido <estrella@ugr.es>, Isabel Pérez <isa@ugr.es>, Tomás Ruiz-Lara <tomasruizlara@gmail.com>, Almudena Zurita <azurita@u
Maintainer-email: Manuel Alcázar-Laynez <manalclay@ugr.es>, Andoni Jimenez <andonijimenez@ugr.es>, Salvador Duarte Puertas <sduarte@ugr.es>, Cristian Pozo González <cpozo@ugr.es>, Jesús Domínguez-Gómez <jesusdg@ugr.es>, Guillermo Blázquez <gblazquez@iaa.es>, Maria del Carmen Argudo-Fernández <margudo@ugr.es>, Simon Verley <simon@ugr.es>
License: MIT License
Project-URL: Homepage, https://gitlab.com/astrogal/GALAssify
Project-URL: Issues, https://gitlab.com/astrogal/GALAssify/-/issues
Keywords: astronomy,astrophysics,classification,galaxies
Classifier: Programming Language :: Python :: 3
Classifier: License :: OSI Approved :: MIT License
Classifier: Operating System :: OS Independent
Classifier: Development Status :: 5 - Production/Stable
Classifier: Environment :: X11 Applications :: Qt
Classifier: Intended Audience :: Science/Research
Classifier: Topic :: Scientific/Engineering :: Astronomy
Classifier: Topic :: Scientific/Engineering :: Physics
Classifier: Topic :: Scientific/Engineering :: Visualization
Requires-Python: >=3.8
License-File: LICENSE
Requires-Dist: wheel
Requires-Dist: pandas>=2.0
Requires-Dist: PyQt5>=5.15
Requires-Dist: matplotlib<3.8; python_version <= "3.10"
Requires-Dist: matplotlib>=3.8; python_version >= "3.11"
Requires-Dist: astropy<=6.1; python_version <= "3.10"
Requires-Dist: astropy>=7.0; python_version >= "3.11"
Requires-Dist: requests>=2.31
Requires-Dist: Pillow>=9.5
Requires-Dist: PyConsoleMenu>=1.0
Provides-Extra: ds9
Requires-Dist: pyds9>=1.8.1; extra == "ds9"
Provides-Extra: doc
Requires-Dist: sphinx; extra == "doc"
Requires-Dist: sphinx-pyproject; extra == "doc"
Requires-Dist: sphinx-rtd-theme; extra == "doc"
Requires-Dist: myst-parser; extra == "doc"
Dynamic: license-file
